setup.cfg
setup.py
traclus_impl/__init__.py
traclus_impl/coordination.py
traclus_impl/distance_functions.py
traclus_impl/generator_initializer.py
traclus_impl/generic_dbscan.py
traclus_impl/geometry.py
traclus_impl/hooks.py
traclus_impl/line_segment_averaging.py
traclus_impl/linked_list.py
traclus_impl/main.py
traclus_impl/mutable_float.py
traclus_impl/parameter_estimation.py
traclus_impl/processed_trajectory_connecting.py
traclus_impl/representative_line_finding.py
traclus_impl/representative_trajectory_average_inputs.py
traclus_impl/simulated_annealing.py
traclus_impl/traclus_dbscan.py
traclus_impl/trajectory.py
traclus_impl/trajectory_partitioning.py
traclus_impl.egg-info/PKG-INFO
traclus_impl.egg-info/SOURCES.txt
traclus_impl.egg-info/dependency_links.txt
traclus_impl.egg-info/not-zip-safe
traclus_impl.egg-info/requires.txt
traclus_impl.egg-info/top_level.txt
traclus_impl/integ_tests/__init__.py
traclus_impl/integ_tests/campus_trajectories_processing_test.py
traclus_impl/integ_tests/campus_trajectories_traclus_output.txt
traclus_impl/integ_tests/clusters_output.txt
traclus_impl/integ_tests/partitioned_stage_output.txt
traclus_impl/integ_tests/raw_campus_trajectories.txt
traclus_impl/integ_tests/whole_cheeseburger_tests.py
traclus_impl/integ_tests/coordination/__init__.py
traclus_impl/integ_tests/coordination/get_all_trajectory_line_segments_from_all_points_integ_tests.py
traclus_impl/integ_tests/deer_tests/__init__.py
traclus_impl/integ_tests/deer_tests/deer_1995.tra
traclus_impl/integ_tests/deer_tests/deer_1995test.tra
traclus_impl/integ_tests/deer_tests/deer_file_reader.py
traclus_impl/integ_tests/deer_tests/dummy_input.txt
traclus_impl/integ_tests/deer_tests/elk_1993.tra
traclus_impl/integ_tests/deer_tests/file_reader_test.py
traclus_impl/integ_tests/deer_tests/hurricane1950_2006.tra
traclus_impl/integ_tests/deer_tests/traclus_runner.py
traclus_impl/integ_tests/parameter_estimation/__init__.py
traclus_impl/integ_tests/parameter_estimation/simulated_annealing_tests.py
traclus_impl/integ_tests/partitioning/__init__.py
traclus_impl/integ_tests/partitioning/encoding_cost_tests.py
traclus_impl/integ_tests/partitioning/hairy_partitioning.txt
