Metadata-Version: 1.0
Name: traclus-impl
Version: 0.9.9
Summary: Implementation of Traclus for 2-D trajectories
Home-page: http://github.com/apolcyn/traclus_impl.git
Author: Alex Polcyn
Author-email: alexpolcyn65@gmail.com
License: MIT
Platform: UNKNOWN
